drain_swamp/__init__.py
drain_swamp/__init__.pyi
drain_swamp/_repr.py
drain_swamp/_repr.pyi
drain_swamp/_version.py
drain_swamp/_version.pyi
drain_swamp/check_type.py
drain_swamp/check_type.pyi
drain_swamp/cli_igor.py
drain_swamp/cli_igor.pyi
drain_swamp/cli_scm_version.py
drain_swamp/cli_scm_version.pyi
drain_swamp/constants.py
drain_swamp/constants.pyi
drain_swamp/constants_maybe.py
drain_swamp/constants_maybe.pyi
drain_swamp/exceptions.py
drain_swamp/exceptions.pyi
drain_swamp/igor_utils.py
drain_swamp/igor_utils.pyi
drain_swamp/package_metadata.py
drain_swamp/package_metadata.pyi
drain_swamp/parser_in.py
drain_swamp/parser_in.pyi
drain_swamp/py.typed
drain_swamp/snippet_sphinx_conf.py
drain_swamp/snippet_sphinx_conf.pyi
drain_swamp/version_semantic.py
drain_swamp/version_semantic.pyi
drain_swamp/monkey/__init__.py
drain_swamp/monkey/config_settings.py
drain_swamp/monkey/config_settings.pyi
drain_swamp/monkey/patch_strftime.py
drain_swamp/monkey/patch_strftime.pyi
drain_swamp/monkey/wrap_get_version.py
drain_swamp/monkey/wrap_get_version.pyi
drain_swamp/monkey/wrap_infer_version.py
drain_swamp/monkey/wrap_infer_version.pyi
drain_swamp/monkey/wrap_version_keyword.py
drain_swamp/monkey/wrap_version_keyword.pyi
drain_swamp/monkey/hooks/__init__.py
drain_swamp/monkey/hooks/__init__.pyi
drain_swamp/monkey/hooks/constants.py
drain_swamp/monkey/hooks/constants.pyi
drain_swamp/monkey/hooks/manager.py
drain_swamp/monkey/hooks/manager.pyi
drain_swamp/monkey/hooks/markers.py
drain_swamp/monkey/hooks/markers.pyi
drain_swamp/monkey/hooks/specs.py
drain_swamp/monkey/hooks/specs.pyi
drain_swamp/monkey/plugins/__init__.py
drain_swamp/monkey/plugins/ds_scm_version.py
drain_swamp/monkey/plugins/ds_scm_version.pyi
drain_swamp/version_file/__init__.py
drain_swamp/version_file/_overrides.py
drain_swamp/version_file/_overrides.pyi
drain_swamp/version_file/dump_version.py
drain_swamp/version_file/dump_version.pyi
drain_swamp-2.1.1.dist-info/LICENSE
drain_swamp-2.1.1.dist-info/METADATA
drain_swamp-2.1.1.dist-info/NOTICE.txt
drain_swamp-2.1.1.dist-info/WHEEL
drain_swamp-2.1.1.dist-info/entry_points.txt
drain_swamp-2.1.1.dist-info/top_level.txt
drain_swamp-2.1.1.dist-info/RECORD
