Metadata-Version: 2.1
Name: drain-swamp
Version: 2.1.1
Summary: Python build backend with build plugins and dependency lock switch
Author-email: Dave Faulkmore <faulkmore@protonmail.com>
License:                     GNU AFFERO GENERAL PUBLIC LICENSE
Project-URL: Documentation, https://msftcangoblowm.github.io/drain-swamp
Project-URL: Docs (rtd), https://drain-swamp.readthedocs.io/en/stable
Project-URL: Changes, https://raw.githubusercontent.com/msftcangoblowm/drain-swamp/master/CHANGES.rst
Project-URL: PyPI Releases, https://pypi.org/project/drain-swamp
Project-URL: Source code, https://github.com/msftcangoblowm/drain-swamp
Project-URL: Issue tracker, https://github.com/msftcangoblowm/drain-swamp/issues
Project-URL: Mastodon, https://mastodon.social/@msftcangoblowme
Keywords: pipenv,pip,pip-tools,dependency lock
Classifier: Environment :: Console
Classifier: Development Status :: 3 - Alpha
Classifier: Intended Audience :: Developers
Classifier: License :: OSI Approved :: GNU Affero General Public License v3 or later (AGPLv3+)
Classifier: Operating System :: OS Independent
Classifier: Programming Language :: Python :: 3
Classifier: Programming Language :: Python :: 3.9
Classifier: Programming Language :: Python :: 3.10
Classifier: Programming Language :: Python :: 3.11
Classifier: Programming Language :: Python :: 3.12
Classifier: Programming Language :: Python :: 3.13
Classifier: Programming Language :: Python :: Implementation :: CPython
Classifier: Programming Language :: Python :: Implementation :: PyPy
Classifier: Topic :: Software Development :: Build Tools
Classifier: Typing :: Typed
Requires-Python: >=3.9
License-File: LICENSE
License-File: NOTICE.txt
Requires-Dist: drain-swamp-snippet
Requires-Dist: pluggy
Requires-Dist: setuptools-scm
Requires-Dist: setuptools>=75.1.0
Requires-Dist: wreck
Provides-Extra: pip
Requires-Dist: packaging==24.2; extra == "pip"
Requires-Dist: setuptools-scm==8.1.0; extra == "pip"
Requires-Dist: tomli==2.2.1; python_version < "3.11" and extra == "pip"
Requires-Dist: typing-extensions==4.12.2; python_version < "3.10" and extra == "pip"
Requires-Dist: pip==24.3.1; extra == "pip"
Requires-Dist: setuptools==75.7.0; extra == "pip"
Provides-Extra: pip-tools
Requires-Dist: build==1.2.2.post1; extra == "pip-tools"
Requires-Dist: click==8.1.8; extra == "pip-tools"
Requires-Dist: importlib-metadata==8.5.0; extra == "pip-tools"
Requires-Dist: packaging==24.2; extra == "pip-tools"
Requires-Dist: pip-tools==7.4.1; extra == "pip-tools"
Requires-Dist: pyproject-hooks==1.2.0; extra == "pip-tools"
Requires-Dist: tomli==2.2.1; python_version < "3.11" and extra == "pip-tools"
Requires-Dist: wheel==0.45.1; extra == "pip-tools"
Requires-Dist: zipp==3.21.0; extra == "pip-tools"
Requires-Dist: pip==24.3.1; extra == "pip-tools"
Requires-Dist: setuptools==75.7.0; extra == "pip-tools"
Provides-Extra: dev
Requires-Dist: appdirs==1.4.4; extra == "dev"
Requires-Dist: attrs==24.3.0; extra == "dev"
Requires-Dist: backports-tarfile==1.1.1; extra == "dev"
Requires-Dist: black==24.4.1; extra == "dev"
Requires-Dist: blackdoc==0.3.9; extra == "dev"
Requires-Dist: bleach==6.2.0; extra == "dev"
Requires-Dist: build==1.2.2.post1; extra == "dev"
Requires-Dist: certifi==2024.8.30; extra == "dev"
Requires-Dist: cffi==1.17.1; extra == "dev"
Requires-Dist: charset-normalizer==3.3.2; extra == "dev"
Requires-Dist: click==8.1.8; extra == "dev"
Requires-Dist: coverage==7.5.0; extra == "dev"
Requires-Dist: cryptography==42.0.5; extra == "dev"
Requires-Dist: docutils==0.21.2; extra == "dev"
Requires-Dist: drain-swamp-snippet==1.0.2; extra == "dev"
Requires-Dist: exceptiongroup==1.2.1; extra == "dev"
Requires-Dist: fastjsonschema==2.19.1; extra == "dev"
Requires-Dist: flake8==7.0.0; extra == "dev"
Requires-Dist: flake8-pyi==24.4.1; extra == "dev"
Requires-Dist: flake8-pyproject==1.2.3; extra == "dev"
Requires-Dist: idna==3.7; extra == "dev"
Requires-Dist: importlib-metadata==8.5.0; extra == "dev"
Requires-Dist: iniconfig==2.0.0; extra == "dev"
Requires-Dist: isort==5.13.2; extra == "dev"
Requires-Dist: jaraco-classes==3.4.0; extra == "dev"
Requires-Dist: jaraco-context==5.3.0; extra == "dev"
Requires-Dist: jaraco-functools==4.0.1; extra == "dev"
Requires-Dist: jeepney==0.8.0; extra == "dev"
Requires-Dist: keyring==25.1.0; extra == "dev"
Requires-Dist: logging-strict==1.4.2; extra == "dev"
Requires-Dist: markdown-it-py==3.0.0; extra == "dev"
Requires-Dist: mccabe==0.7.0; extra == "dev"
Requires-Dist: mdurl==0.1.2; extra == "dev"
Requires-Dist: more-itertools==10.2.0; extra == "dev"
Requires-Dist: mypy==1.10.0; extra == "dev"
Requires-Dist: mypy-extensions==1.0.0; extra == "dev"
Requires-Dist: packaging==24.2; extra == "dev"
Requires-Dist: pathspec==0.12.1; extra == "dev"
Requires-Dist: pip-requirements-parser==32.0.1; extra == "dev"
Requires-Dist: pip-tools==7.4.1; extra == "dev"
Requires-Dist: pkginfo==1.10.0; extra == "dev"
Requires-Dist: platformdirs==4.3.6; extra == "dev"
Requires-Dist: pluggy==1.5.0; extra == "dev"
Requires-Dist: pycodestyle==2.11.1; extra == "dev"
Requires-Dist: pycparser==2.22; extra == "dev"
Requires-Dist: pyflakes==3.2.0; extra == "dev"
Requires-Dist: pygments==2.18.0; extra == "dev"
Requires-Dist: pyparsing==3.2.1; extra == "dev"
Requires-Dist: pyproject-hooks==1.2.0; extra == "dev"
Requires-Dist: pytest==8.1.1; extra == "dev"
Requires-Dist: pytest-datadir==1.5.0; extra == "dev"
Requires-Dist: pytest-logging-strict==0.1.0.post1; extra == "dev"
Requires-Dist: pytest-regressions==2.5.0; extra == "dev"
Requires-Dist: python-dateutil==2.9.0.post0; extra == "dev"
Requires-Dist: pyyaml==6.0.2; extra == "dev"
Requires-Dist: readme-renderer==36.0; extra == "dev"
Requires-Dist: requests==2.32.3; extra == "dev"
Requires-Dist: requests-toolbelt==1.0.0; extra == "dev"
Requires-Dist: rfc3986==2.0.0; extra == "dev"
Requires-Dist: rich==13.7.1; extra == "dev"
Requires-Dist: secretstorage==3.3.3; extra == "dev"
Requires-Dist: setuptools-scm==8.1.0; extra == "dev"
Requires-Dist: six==1.17.0; extra == "dev"
Requires-Dist: strictyaml==1.7.3; extra == "dev"
Requires-Dist: tomli==2.2.1; python_version < "3.11" and extra == "dev"
Requires-Dist: twine==5.0.0; extra == "dev"
Requires-Dist: types-setuptools==70.1.0.20240627; extra == "dev"
Requires-Dist: typing-extensions==4.12.2; python_version < "3.10" and extra == "dev"
Requires-Dist: urllib3==2.2.3; extra == "dev"
Requires-Dist: validate-pyproject==0.16; extra == "dev"
Requires-Dist: webencodings==0.5.1; extra == "dev"
Requires-Dist: wheel==0.45.1; extra == "dev"
Requires-Dist: wreck==0.2.4; extra == "dev"
Requires-Dist: zipp==3.21.0; extra == "dev"
Requires-Dist: pip==24.3.1; extra == "dev"
Requires-Dist: setuptools==75.7.0; extra == "dev"
Provides-Extra: manage
Requires-Dist: backports-tarfile==1.1.1; extra == "manage"
Requires-Dist: bleach==6.2.0; extra == "manage"
Requires-Dist: build==1.2.2.post1; extra == "manage"
Requires-Dist: cachetools==5.5.0; extra == "manage"
Requires-Dist: certifi==2024.8.30; extra == "manage"
Requires-Dist: cffi==1.17.1; extra == "manage"
Requires-Dist: cfgv==3.4.0; extra == "manage"
Requires-Dist: chardet==5.2.0; extra == "manage"
Requires-Dist: charset-normalizer==3.3.2; extra == "manage"
Requires-Dist: click==8.1.8; extra == "manage"
Requires-Dist: colorama==0.4.6; extra == "manage"
Requires-Dist: cryptography==42.0.5; extra == "manage"
Requires-Dist: distlib==0.3.8; extra == "manage"
Requires-Dist: docutils==0.21.2; extra == "manage"
Requires-Dist: drain-swamp-snippet==1.0.2; extra == "manage"
Requires-Dist: filelock==3.13.4; extra == "manage"
Requires-Dist: identify==2.5.36; extra == "manage"
Requires-Dist: idna==3.7; extra == "manage"
Requires-Dist: importlib-metadata==8.5.0; extra == "manage"
Requires-Dist: jaraco-classes==3.4.0; extra == "manage"
Requires-Dist: jaraco-context==5.3.0; extra == "manage"
Requires-Dist: jaraco-functools==4.0.1; extra == "manage"
Requires-Dist: jeepney==0.8.0; extra == "manage"
Requires-Dist: keyring==25.1.0; extra == "manage"
Requires-Dist: markdown-it-py==3.0.0; extra == "manage"
Requires-Dist: mdurl==0.1.2; extra == "manage"
Requires-Dist: more-itertools==10.2.0; extra == "manage"
Requires-Dist: nodeenv==1.8.0; extra == "manage"
Requires-Dist: packaging==24.2; extra == "manage"
Requires-Dist: pip-requirements-parser==32.0.1; extra == "manage"
Requires-Dist: pip-tools==7.4.1; extra == "manage"
Requires-Dist: pkginfo==1.10.0; extra == "manage"
Requires-Dist: platformdirs==4.3.6; extra == "manage"
Requires-Dist: pluggy==1.5.0; extra == "manage"
Requires-Dist: pre-commit==3.7.0; extra == "manage"
Requires-Dist: pycparser==2.22; extra == "manage"
Requires-Dist: pygments==2.18.0; extra == "manage"
Requires-Dist: pyparsing==3.2.1; extra == "manage"
Requires-Dist: pyproject-api==1.8.0; extra == "manage"
Requires-Dist: pyproject-hooks==1.2.0; extra == "manage"
Requires-Dist: pyyaml==6.0.2; extra == "manage"
Requires-Dist: readme-renderer==36.0; extra == "manage"
Requires-Dist: requests==2.32.3; extra == "manage"
Requires-Dist: requests-toolbelt==1.0.0; extra == "manage"
Requires-Dist: restview==3.0.1; extra == "manage"
Requires-Dist: rfc3986==2.0.0; extra == "manage"
Requires-Dist: rich==13.7.1; extra == "manage"
Requires-Dist: secretstorage==3.3.3; extra == "manage"
Requires-Dist: setuptools-scm==8.1.0; extra == "manage"
Requires-Dist: tomli==2.2.1; python_version < "3.11" and extra == "manage"
Requires-Dist: tox==4.15.1; extra == "manage"
Requires-Dist: tox-gh-actions==3.2.0; extra == "manage"
Requires-Dist: twine==5.0.0; extra == "manage"
Requires-Dist: typing-extensions==4.12.2; python_version < "3.10" and extra == "manage"
Requires-Dist: urllib3==2.2.3; extra == "manage"
Requires-Dist: virtualenv==20.26.0; extra == "manage"
Requires-Dist: webencodings==0.5.1; extra == "manage"
Requires-Dist: wheel==0.45.1; extra == "manage"
Requires-Dist: wreck==0.2.4; extra == "manage"
Requires-Dist: zipp==3.21.0; extra == "manage"
Requires-Dist: pip==24.3.1; extra == "manage"
Requires-Dist: setuptools==75.7.0; extra == "manage"
Provides-Extra: docs
Requires-Dist: alabaster==1.0.0; extra == "docs"
Requires-Dist: anyio==4.7.0; extra == "docs"
Requires-Dist: attrs==24.2.0; extra == "docs"
Requires-Dist: babel==2.16.0; extra == "docs"
Requires-Dist: build==1.2.2.post1; extra == "docs"
Requires-Dist: certifi==2024.8.30; extra == "docs"
Requires-Dist: charset-normalizer==3.4.0; extra == "docs"
Requires-Dist: click==8.1.7; extra == "docs"
Requires-Dist: click-log==0.4.0; extra == "docs"
Requires-Dist: colorama==0.4.6; extra == "docs"
Requires-Dist: docutils==0.21.2; extra == "docs"
Requires-Dist: dom-toml==2.0.0; extra == "docs"
Requires-Dist: domdf-python-tools==3.9.0; extra == "docs"
Requires-Dist: drain-swamp-snippet==1.0.1; extra == "docs"
Requires-Dist: exceptiongroup==1.2.2; extra == "docs"
Requires-Dist: h11==0.14.0; extra == "docs"
Requires-Dist: idna==3.10; extra == "docs"
Requires-Dist: imagesize==1.4.1; extra == "docs"
Requires-Dist: importlib-metadata==8.5.0; extra == "docs"
Requires-Dist: interrogate==1.7.0; extra == "docs"
Requires-Dist: jinja2==3.1.4; extra == "docs"
Requires-Dist: jsonschema==4.23.0; extra == "docs"
Requires-Dist: jsonschema-specifications==2024.10.1; extra == "docs"
Requires-Dist: markdown-it-py==3.0.0; extra == "docs"
Requires-Dist: markupsafe==3.0.2; extra == "docs"
Requires-Dist: mdit-py-plugins==0.4.2; extra == "docs"
Requires-Dist: mdurl==0.1.2; extra == "docs"
Requires-Dist: myst-parser==4.0.0; extra == "docs"
Requires-Dist: natsort==8.4.0; extra == "docs"
Requires-Dist: packaging==24.2; extra == "docs"
Requires-Dist: pip-requirements-parser==32.0.1; extra == "docs"
Requires-Dist: pip-tools==7.4.1; extra == "docs"
Requires-Dist: pluggy==1.5.0; extra == "docs"
Requires-Dist: py==1.11.0; extra == "docs"
Requires-Dist: pygments==2.18.0; extra == "docs"
Requires-Dist: pyparsing==3.2.0; extra == "docs"
Requires-Dist: pyproject-hooks==1.2.0; extra == "docs"
Requires-Dist: python-dateutil==2.9.0.post0; extra == "docs"
Requires-Dist: pyyaml==6.0.2; extra == "docs"
Requires-Dist: referencing==0.35.1; extra == "docs"
Requires-Dist: requests==2.32.3; extra == "docs"
Requires-Dist: rpds-py==0.22.3; extra == "docs"
Requires-Dist: scriv==1.5.1; extra == "docs"
Requires-Dist: setuptools-scm==8.1.0; extra == "docs"
Requires-Dist: six==1.17.0; extra == "docs"
Requires-Dist: sniffio==1.3.1; extra == "docs"
Requires-Dist: snowballstemmer==2.2.0; extra == "docs"
Requires-Dist: sphinx==8.1.3; extra == "docs"
Requires-Dist: sphinx-autobuild==2024.10.3; extra == "docs"
Requires-Dist: sphinx-copybutton==0.5.2; extra == "docs"
Requires-Dist: sphinx-design==0.6.1; extra == "docs"
Requires-Dist: sphinx-external-toc-strict==2.0.1; extra == "docs"
Requires-Dist: sphinx-favicon==1.0.1; extra == "docs"
Requires-Dist: sphinx-paramlinks==0.6.0; extra == "docs"
Requires-Dist: sphinx-pyproject==0.3.0; extra == "docs"
Requires-Dist: sphinx-tabs==3.4.7; extra == "docs"
Requires-Dist: sphinxcontrib-applehelp==2.0.0; extra == "docs"
Requires-Dist: sphinxcontrib-devhelp==2.0.0; extra == "docs"
Requires-Dist: sphinxcontrib-htmlhelp==2.1.0; extra == "docs"
Requires-Dist: sphinxcontrib-jsmath==1.0.1; extra == "docs"
Requires-Dist: sphinxcontrib-qthelp==2.0.0; extra == "docs"
Requires-Dist: sphinxcontrib-serializinghtml==2.0.0; extra == "docs"
Requires-Dist: sphobjinv==2.3.1.1; extra == "docs"
Requires-Dist: starlette==0.41.3; extra == "docs"
Requires-Dist: strictyaml==1.7.3; extra == "docs"
Requires-Dist: tabulate==0.9.0; extra == "docs"
Requires-Dist: tomli==2.2.1; python_version < "3.11" and extra == "docs"
Requires-Dist: typing-extensions==4.12.2; extra == "docs"
Requires-Dist: urllib3==2.2.3; extra == "docs"
Requires-Dist: uvicorn==0.32.1; extra == "docs"
Requires-Dist: watchfiles==1.0.3; extra == "docs"
Requires-Dist: websockets==14.1; extra == "docs"
Requires-Dist: wheel==0.45.1; extra == "docs"
Requires-Dist: wreck==0.2.1; extra == "docs"
Requires-Dist: zipp==3.21.0; extra == "docs"
Requires-Dist: pip==24.1.2; extra == "docs"
Requires-Dist: setuptools==75.6.0; extra == "docs"
